seahash-0.2.0.dist-info/METADATA
seahash-0.2.0.dist-info/WHEEL
seahash-0.2.0.dist-info/license_files/LICENSE
seahash/__init__.py
seahash/__init__.pyi
seahash/py.typed
seahash/seahash.cpython-39-darwin.so
seahash-0.2.0.dist-info/RECORD
