Metadata-Version: 2.1
Name: seahash
Version: 0.2.0
Classifier: Programming Language :: Rust
Classifier: Programming Language :: Python :: Implementation :: CPython
Classifier: Programming Language :: Python :: Implementation :: PyPy
Classifier: Programming Language :: Python :: 3
Classifier: Programming Language :: Python :: 3.7
Classifier: Programming Language :: Python :: 3.8
Classifier: Programming Language :: Python :: 3.9
Classifier: Programming Language :: Python :: 3.10
Classifier: Development Status :: 4 - Beta
Classifier: License :: OSI Approved :: MIT License
Classifier: Typing :: Typed
Requires-Dist: pytest==7.1.2; extra == 'dev'
Requires-Dist: black==22.6.0; extra == 'dev'
Provides-Extra: dev
License-File: LICENSE
Summary: A blazingly fast, portable hash function with proven statistical guarantees
Keywords: hash,hashing,checksum,checksumming,portable
License: MIT
Requires-Python: >=3.7
Project-URL: Issues, https://github.com/RealOrangeOne/seahash-py/issues
Project-URL: Changelog, https://github.com/RealOrangeOne/seahash-py/releases
Project-URL: Source, https://github.com/RealOrangeOne/seahash-py
